realtime_talib/Constants.py
realtime_talib/Indicator.py
realtime_talib/TalibWrapper.py
realtime_talib/Utilities.py
realtime_talib/__init__.py
realtime_talib-0.25.dist-info/DESCRIPTION.rst
realtime_talib-0.25.dist-info/METADATA
realtime_talib-0.25.dist-info/RECORD
realtime_talib-0.25.dist-info/WHEEL
realtime_talib-0.25.dist-info/metadata.json
realtime_talib-0.25.dist-info/top_level.txt
