Metadata-Version: 2.0
Name: realtime-talib
Version: 0.25
Summary: Generate Realtime technical indicators for algotrading/fun
Home-page: https://github.com/themichaelusa/realtime_talib
Author: Michael Usachenko
Author-email: meu2@illinois.edu
License: UNKNOWN
Download-URL: https://github.com/themichaelusa/realtime_talib/archive/0.25.tar.gz
Keywords: realtime,talib
Platform: UNKNOWN
Requires-Dist: TA-Lib
Requires-Dist: numpy
